elidas_primos/__init__.py
elidas_primos-1.0.dist-info/LICENSE
elidas_primos-1.0.dist-info/METADATA
elidas_primos-1.0.dist-info/WHEEL
elidas_primos-1.0.dist-info/top_level.txt
elidas_primos-1.0.dist-info/RECORD
