Metadata-Version: 2.1
Name: elidas-primos
Version: 1.0
Summary: A tool to get primal numbers in a range
Home-page: UNKNOWN
Author: Oscar Gutierrez
Author-email: UNKNOWN
License: GNUGPLv3
Keywords: pyoperaciones mathematical operations
Platform: UNKNOWN
Classifier: Development Status :: 4 - Beta
Classifier: Intended Audience :: Developers
Classifier: Topic :: Utilities
Classifier: License :: OSI Approved :: GNU General Public License v3 (GPLv3)
Classifier: Operating System :: OS Independent
